source/fsm_controller.v
module fsm_controller (
    input wire clk,
    input wire rst,
    input wire start,
    output reg load,
    output reg execute,
    output reg done
);
    parameter IDLE=2'b00;
    parameter LOAD=2'b01;
    parameter EXECUTE=2'b10;
    parameter DONE=2'b11;
    reg [1:0] current_state;
    reg [1:0] next_state;
    always @(posedge clk or posedge rst)
        begin
            if(rst)
                current_state<=IDLE;
            else
                current_state<=next_state; 
        end
    always @(*)
        begin
            next_state=current_state;
            case (current_state)
                IDLE:
                    begin
                        if (start)
                            next_state=LOAD;
                    end
                LOAD:
                    begin
                        next_state=EXECUTE;
                    end
                EXECUTE:
                    begin
                        next_state=DONE;
                    end
                DONE:
                    begin
                        next_state=IDLE;
                    end
                default:
                    begin
                        next_state=IDLE;
                    end
            endcase
        end
        always @(*)
            begin
                load=1'b0;
                execute=1'b0;
                done=1'b0;
                case(current_state)
                    LOAD:
                        load=1'b1;
                    EXECUTE:
                        execute=1'b1;
                    DONE:
                        done=1'b1;
                endcase
            end
endmodule

test_bench/new_fsm_tb.v
module fsm_abuse_tb;

    reg clk;
    reg rst;
    reg start;

    wire load;
    wire execute;
    wire done;

    fsm_controller dut (
        .clk(clk),
        .rst(rst),
        .start(start),
        .load(load),
        .execute(execute),
        .done(done)
    );

    always #5 clk = ~clk;

    initial begin
        clk = 0;
        rst = 1;
        start = 0;

        $dumpfile("fsm_abuse.vcd");
        $dumpvars(0, fsm_abuse_tb);

        #10 rst = 0;

        #10 start = 1;
        #30 start = 0;

        #50;

        #10 start = 1;
        #10 start = 0;
        #10 start = 1; 
        #10 start = 0;

        #60;

        #10 start = 1; #10 start = 0;
        #10 start = 1; #10 start = 0;

        #80;

        #10 start = 1; #10 start = 0;
        #20 rst = 1;
        #10 rst = 0;

        #50;

        $finish;
    end

endmodule

GTK_Wave/fsm_abuse.vcd
$date
	Sun Jan 18 20:02:33 2026
$end
$version
	Icarus Verilog
$end
$timescale
	1s
$end
$scope module fsm_abuse_tb $end
$var wire 1 ! load $end
$var wire 1 " execute $end
$var wire 1 # done $end
$var reg 1 $ clk $end
$var reg 1 % rst $end
$var reg 1 & start $end
$scope module dut $end
$var wire 1 $ clk $end
$var wire 1 % rst $end
$var wire 1 & start $end
$var reg 2 ' current_state [1:0] $end
$var reg 1 # done $end
$var reg 1 " execute $end
$var reg 1 ! load $end
$var reg 2 ( next_state [1:0] $end
$upscope $end
$upscope $end
$enddefinitions $end
#0
$dumpvars
b0 (
b0 '
0&
1%
0$
0#
0"
0!
$end
#5
1$
#10
0$
0%
#15
1$
#20
b1 (
0$
1&
#25
1!
b10 (
b1 '
1$
#30
0$
#35
1"
0!
b11 (
b10 '
1$
#40
0$
#45
1#
0"
b0 (
b11 '
1$
#50
b0 (
0$
0&
#55
0#
b0 '
1$
#60
0$
#65
1$
#70
0$
#75
1$
#80
0$
#85
1$
#90
0$
#95
1$
#100
0$
#105
1$
#110
b1 (
0$
1&
#115
1!
b10 (
b1 '
1$
#120
b10 (
0$
0&
#125
1"
0!
b11 (
b10 '
1$
#130
b11 (
0$
1&
#135
1#
0"
b0 (
b11 '
1$
#140
b0 (
0$
0&
#145
0#
b0 '
1$
#150
0$
#155
1$
#160
0$
#165
1$
#170
0$
#175
1$
#180
0$
#185
1$
#190
0$
#195
1$
#200
0$
#205
1$
#210
b1 (
0$
1&
#215
1!
b10 (
b1 '
1$
#220
b10 (
0$
0&
#225
1"
0!
b11 (
b10 '
1$
#230
b11 (
0$
1&
#235
1#
0"
b0 (
b11 '
1$
#240
b0 (
0$
0&
#245
0#
b0 '
1$
#250
0$
#255
1$
#260
0$
#265
1$
#270
0$
#275
1$
#280
0$
#285
1$
#290
0$
#295
1$
#300
0$
#305
1$
#310
0$
#315
1$
#320
0$
#325
1$
#330
b1 (
0$
1&
#335
1!
b10 (
b1 '
1$
#340
b10 (
0$
0&
#345
1"
0!
b11 (
b10 '
1$
#350
0$
#355
1#
0"
b0 (
b11 '
1$
#360
0#
b0 '
0$
1%
#365
1$
#370
0$
0%
