source/alu.v
module alu #(parameter WIDTH=8)
    (input wire [WIDTH-1:0] A,
    input wire [WIDTH-1:0] B,
    input wire [2:0] ALU_Sel,
    output reg [WIDTH-1:0] ALU_Out,
    output reg Zero,
    output reg Carry,
    output reg Negative);
    reg [WIDTH:0] temp;
always @(*)
begin
    ALU_Out  = {WIDTH{1'b0}};
    Carry    = 1'b0;
    Zero     = 1'b0;
    Negative = 1'b0;
    temp     = {WIDTH+1{1'b0}};
       case (ALU_Sel)
            3'b000: begin // ADD
                temp    = A + B;
                ALU_Out = temp[WIDTH-1:0];
                Carry   = temp[WIDTH];
            end

            3'b001: begin // SUB
                temp    = A - B;
                ALU_Out = temp[WIDTH-1:0];
                Carry   = temp[WIDTH]; // borrow flag style
            end

            3'b010: ALU_Out = A & B;
            3'b011: ALU_Out = A | B;
            3'b100: ALU_Out = A ^ B;
            3'b101: ALU_Out = A <<1;
            3'b110: ALU_Out = A >>1;
            3'b111: ALU_Out = {WIDTH{1'b0}};
            default:ALU_Out={WIDTH{1'b0}};
       endcase
       Zero     = (ALU_Out == {WIDTH{1'b0}});
       Negative = ALU_Out[WIDTH-1];
end
endmodule

alu_tb.v
module alu_tb;
    parameter WIDTH=8;
    reg [WIDTH-1:0] A;
    reg [WIDTH-1:0] B;
    reg [2:0] ALU_Sel;
    wire [WIDTH-1:0] ALU_Out;
    wire Zero;
    wire Carry;
    wire Negative;
    alu #(.WIDTH(WIDTH)) dut (
        .A(A),
        .B(B),
        .Zero(Zero),
        .Carry(Carry),
        .Negative(Negative),
        .ALU_Sel(ALU_Sel),
        .ALU_Out(ALU_Out));
    initial
     begin
        $dumpfile("alu.vcd");
        $dumpvars(0,alu_tb);
        A=8'd10; B=8'd5; ALU_Sel=3'b000; #10;
        A=8'd10; B=8'd3; ALU_Sel=3'b001; #10;
        A=8'b10101010; B=8'b11001100; ALU_Sel=3'b010; #10;
        A=8'b10101010; B=8'b11001100; ALU_Sel=3'b011; #10;
        A=8'b10101010; B=8'b11001100; ALU_Sel=3'b100; #10;
        A=8'b00001111; B=8'd1; ALU_Sel=3'b101; #10;
        A=8'b11110000; B=8'd1; ALU_Sel=3'b110; #10;
        A=8'hFF;B=8'hFF;ALU_Sel=3'b111; #10;
        $finish;   
    end
endmodule

source/alu.vcd
$date
	Thu Jan 08 05:25:14 2026
$end
$version
	Icarus Verilog
$end
$timescale
	1s
$end
$scope module alu_tb $end
$var wire 1 ! Zero $end
$var wire 1 " Negative $end
$var wire 1 # Carry $end
$var wire 8 $ ALU_Out [7:0] $end
$var reg 8 % A [7:0] $end
$var reg 3 & ALU_Sel [2:0] $end
$var reg 8 ' B [7:0] $end
$scope module dut $end
$var wire 8 ( A [7:0] $end
$var wire 3 ) ALU_Sel [2:0] $end
$var wire 8 * B [7:0] $end
$var reg 8 + ALU_Out [7:0] $end
$var reg 1 # Carry $end
$var reg 1 " Negative $end
$var reg 1 ! Zero $end
$var reg 9 , temp [8:0] $end
$upscope $end
$upscope $end
$enddefinitions $end
#0
$dumpvars
b1111 ,
b1111 +
b101 *
b0 )
b1010 (
b101 '
b0 &
b1010 %
b1111 $
0#
0"
0!
$end
#10
b111 ,
b111 $
b111 +
b1 &
b1 )
b11 '
b11 *
#20
1"
b0 ,
b10001000 $
b10001000 +
b10 &
b10 )
b11001100 '
b11001100 *
b10101010 %
b10101010 (
#30
1"
b11101110 $
b11101110 +
b11 &
b11 )
#40
0"
b1100110 $
b1100110 +
b100 &
b100 )
#50
b11110 $
b11110 +
b101 &
b101 )
b1 '
b1 *
b1111 %
b1111 (
#60
b1111000 $
b1111000 +
b110 &
b110 )
b11110000 %
b11110000 (
#70
1!
b0 $
b0 +
b111 &
b111 )
b11111111 '
b11111111 *
b11111111 %
b11111111 (
